Metadata-Version: 2.4
Name: pyramid_formencode_classic
Version: 0.12.0
Summary: An implementation of the classic Pylons formencode validation, for Pyramid.
Home-page: https://github.com/jvanasco/pyramid_formencode_classic
Author: Jonathan Vanasco
Author-email: jonathan@findmeon.com
License: BSD
Classifier: Intended Audience :: Developers
Classifier: Framework :: Pyramid
Classifier: Programming Language :: Python
Classifier: Programming Language :: Python :: 3
Classifier: Programming Language :: Python :: 3.7
Classifier: Programming Language :: Python :: 3.8
Classifier: Programming Language :: Python :: 3.9
Classifier: Programming Language :: Python :: 3.10
Classifier: Programming Language :: Python :: 3.11
Classifier: Programming Language :: Python :: 3.12
Classifier: Programming Language :: Python :: 3.13
Requires-Dist: pyramid
Requires-Dist: formencode>=2.0.0
Requires-Dist: typing_extensions
Provides-Extra: testing
Requires-Dist: pytest; extra == "testing"
Requires-Dist: mypy; extra == "testing"
Requires-Dist: pyramid_mako; extra == "testing"
Requires-Dist: webob; extra == "testing"
Dynamic: author
Dynamic: author-email
Dynamic: classifier
Dynamic: description
Dynamic: description-content-type
Dynamic: home-page
Dynamic: license
Dynamic: provides-extra
Dynamic: requires-dist
Dynamic: summary
